{"PhotoDescription": "A woman is lying on a bed with her legs spread out and her hands on her crotch. She appears to be in a relaxed and comfortable position.", "ActionsDescription": "The person in the image is posing for a picture while lying naked on a bed.", "HairColor": "Gray", "HairStyle": "Straight", "Physique": "No idea", "BustSize": "Small", "AgeGroup": "Middle-aged", "FacialExpression": "Smiling", "ClothingCategory": "No", "WornAccessories": "No", "SkinTone": "Light", "BodyPosture": "Sexy pose", "GeneralLocation": "Bedroom", "PersonOrientation": "Front", "ShotContextFocus": "Chest", "ImageType": "Candid"}