{"PhotoDescription": "A woman wearing a pink bra and necklace is standing in front of a wall.", "ActionsDescription": "The person in the image is wearing a pink bra and a necklace. They are smiling and showing off their breasts.", "HairColor": "Blond", "HairStyle": "No idea", "Physique": "No idea", "BustSize": "Large", "AgeGroup": "Senior", "FacialExpression": "Smile", "ClothingCategory": "Topless", "WornAccessories": "Necklace", "SkinTone": "Light", "BodyPosture": "Exposing", "GeneralLocation": "Indoors", "PersonOrientation": "Front", "ShotContextFocus": "Chest", "ImageType": "Close-up"}