{"PhotoDescription": "A woman wearing a grey dress and a grey sweater is taking a selfie. She is wearing a ring on her finger and has her hand up to her chest.", "ActionsDescription": "The person in the image is taking a selfie, showing off her breasts and a skirt.", "HairColor": "Blond", "HairStyle": "No idea", "Physique": "No idea", "BustSize": "Large", "AgeGroup": "Young adult", "FacialExpression": "Neutral", "ClothingCategory": "No", "WornAccessories": "No", "SkinTone": "Light", "BodyPosture": "Exposing", "GeneralLocation": "Indoors", "PersonOrientation": "Front", "ShotContextFocus": "Chest", "ImageType": "Close-up"}