{"PhotoDescription": "A woman with blonde hair wearing a red lace bra and posing for a picture.", "ActionsDescription": "The person in the image is posing for a picture while wearing a red lingerie top.", "HairColor": "Blonde", "HairStyle": "Wavy", "Physique": "No idea", "BustSize": "Large", "AgeGroup": "Young adult", "FacialExpression": "No idea", "ClothingCategory": "Topless", "WornAccessories": "No", "SkinTone": "Light", "BodyPosture": "Sexy pose", "GeneralLocation": "Indoors", "PersonOrientation": "Front", "ShotContextFocus": "Face", "ImageType": "Portrait"}