{"PhotoDescription": "A person is laying on a couch, with their hands on their stomach. The couch has a floral pattern, and the person appears to be naked.", "ActionsDescription": "The person in the image is laying down and touching their stomach.", "HairColor": "Brown", "HairStyle": "No", "Physique": "No idea", "BustSize": "Large", "AgeGroup": "Middle-aged", "FacialExpression": "Neutral", "ClothingCategory": "No", "WornAccessories": "No", "SkinTone": "Light", "BodyPosture": "No", "GeneralLocation": "Indoors", "PersonOrientation": "No information", "ShotContextFocus": "Chest", "ImageType": "Close-up"}