{"PhotoDescription": "A woman wearing a strapless dress and stockings is sitting on a couch, posing for the camera. She has her legs spread out and is smiling.", "ActionsDescription": "The person in the image is posing on a couch, wearing a strapless dress and stockings.", "HairColor": "Blonde", "HairStyle": "No idea", "Physique": "No idea", "BustSize": "Small", "AgeGroup": "Senior", "FacialExpression": "Smiling", "ClothingCategory": "No", "WornAccessories": "No", "SkinTone": "Light", "BodyPosture": "Sexy pose", "GeneralLocation": "Indoors", "PersonOrientation": "Front", "ShotContextFocus": "Face", "ImageType": "Portrait"}