{"PhotoDescription": "A woman wearing a bikini top and sunglasses poses for a picture.", "ActionsDescription": "The person in the image is taking a selfie.", "HairColor": "Black", "HairStyle": "Wavy", "Physique": "No idea", "BustSize": "Small", "AgeGroup": "Young adult", "FacialExpression": "No idea", "ClothingCategory": "Swimwear", "WornAccessories": "Sunglasses", "SkinTone": "Light", "BodyPosture": "Sexy pose", "GeneralLocation": "Outdoors", "PersonOrientation": "Front", "ShotContextFocus": "Face", "ImageType": "Portrait"}