{"PhotoDescription": "A woman with long hair is sitting on a couch, her body partially exposed. She has her hands on her lap and her legs crossed. The image does not contain any text or other discernible objects.", "ActionsDescription": "The person in the image is sitting on a chair with their legs crossed.", "HairColor": "Black", "HairStyle": "Wavy", "Physique": "No idea", "BustSize": "Small", "AgeGroup": "Middle-aged", "FacialExpression": "No idea", "ClothingCategory": "No", "WornAccessories": "Ring", "SkinTone": "Light", "BodyPosture": "No idea", "GeneralLocation": "Outdoors", "PersonOrientation": "No idea", "ShotContextFocus": "Face", "ImageType": "Close-up"}