{"PhotoDescription": "A woman with blonde hair is showing her breasts in a mirror. She is wearing a black shirt and has a ring on her finger. The woman's hands are positioned over her breasts, and she appears to be looking at her reflection.", "ActionsDescription": "The person in the image is showing off her breasts, possibly for a photo or to share with others.", "HairColor": "Blond", "HairStyle": "Wavy", "Physique": "No idea", "BustSize": "Large", "AgeGroup": "Middle-aged", "FacialExpression": "Neutral", "ClothingCategory": "No", "WornAccessories": "No", "SkinTone": "Light", "BodyPosture": "Exposing", "GeneralLocation": "Indoors", "PersonOrientation": "Front", "ShotContextFocus": "Chest", "ImageType": "Close-up"}