{"PhotoDescription": "A woman wearing a black lace dress and stockings is lying on a couch.", "ActionsDescription": "The person in the image is laying down on a couch, wearing a black lace outfit.", "HairColor": "Black", "HairStyle": "No idea", "Physique": "No idea", "BustSize": "Small", "AgeGroup": "Teenager", "FacialExpression": "No idea", "ClothingCategory": "Fully nude", "WornAccessories": "No", "SkinTone": "Light", "BodyPosture": "Lying down", "GeneralLocation": "Indoors", "PersonOrientation": "No idea", "ShotContextFocus": "Legs", "ImageType": "Portrait"}