{"PhotoDescription": "A woman with long hair wearing a yellow lace top and posing for a picture.", "ActionsDescription": "The person in the image is posing for a picture, wearing a yellow lace top or robe.", "HairColor": "Brown", "HairStyle": "No idea", "Physique": "No idea", "BustSize": "Large", "AgeGroup": "Middle-aged", "FacialExpression": "Frowning", "ClothingCategory": "Tops", "WornAccessories": "No", "SkinTone": "Light", "BodyPosture": "Sexy pose", "GeneralLocation": "Indoors", "PersonOrientation": "Front", "ShotContextFocus": "Face", "ImageType": "Portrait"}