{"PhotoDescription": "A woman with curly blonde hair is sitting on a bed, wearing only her bra and showing her chest. She is looking off to the side with a concerned expression.", "ActionsDescription": "The person in the image is sitting on a bed and pointing at her chest.", "HairColor": "Blonde", "HairStyle": "Curly", "Physique": "No", "BustSize": "Small", "AgeGroup": "Middle-aged", "FacialExpression": "Frowning", "ClothingCategory": "Tops", "WornAccessories": "No", "SkinTone": "Light", "BodyPosture": "No", "GeneralLocation": "Indoors", "PersonOrientation": "Front", "ShotContextFocus": "Face", "ImageType": "Close-up"}