{"PhotoDescription": "A woman wearing a bikini top and underwear is taking a selfie in front of a mirror. She is standing in a room with a bed visible in the background.", "ActionsDescription": "The person in the image is taking a selfie using a mirror.", "HairColor": "Brown", "HairStyle": "No idea", "Physique": "Athletic", "BustSize": "Small", "AgeGroup": "Young adult", "FacialExpression": "Frowning", "ClothingCategory": "Fully nude", "WornAccessories": "Necklace", "SkinTone": "Light", "BodyPosture": "Sexy pose", "GeneralLocation": "Indoors", "PersonOrientation": "Front", "ShotContextFocus": "Butt", "ImageType": "Portrait"}