{"PhotoDescription": "A woman is laying on a bed, wearing a leopard print bikini top and bikini bottoms. She is curled up in a relaxed position, possibly enjoying a moment of rest or intimacy.", "ActionsDescription": "The person in the image is laying down on a bed, possibly in a relaxed or intimate position.", "HairColor": "Brown", "HairStyle": "No idea", "Physique": "No idea", "BustSize": "Large", "AgeGroup": "Teenager", "FacialExpression": "No idea", "ClothingCategory": "No", "WornAccessories": "Earrings", "SkinTone": "Light", "BodyPosture": "Sexy pose", "GeneralLocation": "Indoors", "PersonOrientation": "No", "ShotContextFocus": "Butt", "ImageType": "Close-up"}