{"PhotoDescription": "A person is taking a selfie in a bathroom. The bathroom features a sink and a mirror, and there are toothbrushes placed nearby. The person appears to be naked, with their belly and chest visible in the image.", "ActionsDescription": "The person in the image is taking a selfie, likely in a bathroom setting.", "HairColor": "No idea", "HairStyle": "No idea", "Physique": "No idea", "BustSize": "Small", "AgeGroup": "No idea", "FacialExpression": "No idea", "ClothingCategory": "No", "WornAccessories": "No", "SkinTone": "Light", "BodyPosture": "Sexy pose", "GeneralLocation": "Bathroom", "PersonOrientation": "Front", "ShotContextFocus": "Chest", "ImageType": "Candid"}