{"PhotoDescription": "A woman with long wavy hair is sitting in a bathtub, looking at the camera.", "ActionsDescription": "The person in the image is sitting in a bathtub with her chest exposed.", "HairColor": "Brown", "HairStyle": "Wavy", "Physique": "No idea", "BustSize": "Small", "AgeGroup": "Teenager", "FacialExpression": "No idea", "ClothingCategory": "No", "WornAccessories": "No", "SkinTone": "Light", "BodyPosture": "No idea", "GeneralLocation": "Bathroom", "PersonOrientation": "Overhead", "ShotContextFocus": "Face", "ImageType": "Candid"}