{"PhotoDescription": "A naked woman is standing in a kitchen, holding a pair of chopsticks. She is posing for a photo in front of a stove and a countertop.", "ActionsDescription": "The person in the image is posing naked in a kitchen, holding chopsticks.", "HairColor": "Blonde", "HairStyle": "No idea", "Physique": "No idea", "BustSize": "Small", "AgeGroup": "Young adult", "FacialExpression": "Smiling", "ClothingCategory": "No", "WornAccessories": "No", "SkinTone": "Light", "BodyPosture": "Sexy pose", "GeneralLocation": "Indoors", "PersonOrientation": "Front", "ShotContextFocus": "No", "ImageType": "Candid"}