{"PhotoDescription": "A woman is lying down on a bed, wearing a black bra. She has a pink mark on her body, possibly from a recent surgery.", "ActionsDescription": "The person in the image is laying down on a bed, with their body covered by a black bra.", "HairColor": "No idea", "HairStyle": "No idea", "Physique": "No idea", "BustSize": "Small", "AgeGroup": "Teenager", "FacialExpression": "Neutral", "ClothingCategory": "No", "WornAccessories": "No", "SkinTone": "Light", "BodyPosture": "Lying down", "GeneralLocation": "Indoors", "PersonOrientation": "Front", "ShotContextFocus": "Chest", "ImageType": "Close-up"}