{"PhotoDescription": "A woman is standing in front of a window with her hands on her hips. She is wearing black shoes and appears to be barefoot. The window has blinds, and there is a lamp next to it. The woman is smiling and seems to be posing for the camera.", "ActionsDescription": "The person in the image is posing for a picture, standing in front of a window.", "HairColor": "Blonde", "HairStyle": "No idea", "Physique": "No idea", "BustSize": "Small", "AgeGroup": "Senior", "FacialExpression": "Smiling", "ClothingCategory": "No", "WornAccessories": "No", "SkinTone": "Light", "BodyPosture": "Sexy pose", "GeneralLocation": "Indoors", "PersonOrientation": "Front", "ShotContextFocus": "No", "ImageType": "Portrait"}